wmflib/__init__.py
wmflib/actions.py
wmflib/config.py
wmflib/constants.py
wmflib/decorators.py
wmflib/dns.py
wmflib/exceptions.py
wmflib/fileio.py
wmflib/idm.py
wmflib/interactive.py
wmflib/irc.py
wmflib/phabricator.py
wmflib/prometheus.py
wmflib/py.typed
wmflib/requests.py
wmflib-2.0.0.dist-info/licenses/LICENSE
wmflib-2.0.0.dist-info/METADATA
wmflib-2.0.0.dist-info/WHEEL
wmflib-2.0.0.dist-info/top_level.txt
wmflib-2.0.0.dist-info/RECORD
