Metadata-Version: 2.4
Name: wmflib
Version: 2.0.0
Summary: Generic library for common tasks in the WMF production infrastructure
Home-page: https://github.com/wikimedia/operations-software-pywmflib
Author: Luca Toscano
Author-email: ltoscano@wikimedia.org
License: GPLv3+
Keywords: wmf,automation
Platform: GNU/Linux
Classifier: Development Status :: 2 - Pre-Alpha
Classifier: Environment :: Console
Classifier: Intended Audience :: System Administrators
Classifier: License :: OSI Approved :: GNU General Public License v3 or later (GPLv3+)
Classifier: Operating System :: MacOS :: MacOS X
Classifier: Operating System :: POSIX :: BSD
Classifier: Operating System :: POSIX :: Linux
Classifier: Programming Language :: Python :: 3.7
Classifier: Programming Language :: Python :: 3.8
Classifier: Programming Language :: Python :: 3.9
Classifier: Programming Language :: Python :: 3.10
Classifier: Programming Language :: Python :: 3.11
Classifier: Programming Language :: Python :: 3.12
Classifier: Programming Language :: Python :: 3.13
Classifier: Programming Language :: Python :: 3 :: Only
Classifier: Topic :: Software Development :: Libraries :: Python Modules
Classifier: Topic :: System :: Systems Administration
Requires-Python: >=3.7
License-File: LICENSE
Requires-Dist: dnspython>=1.15.0
Requires-Dist: pyyaml>=3.11
Requires-Dist: phabricator>=0.7.0
Requires-Dist: requests
Provides-Extra: tests
Requires-Dist: bandit>=1.5.1; extra == "tests"
Requires-Dist: flake8>=3.2.1; extra == "tests"
Requires-Dist: flake8-import-order>=0.18.1; extra == "tests"
Requires-Dist: mypy>=0.470; extra == "tests"
Requires-Dist: pytest>=3.10.1; extra == "tests"
Requires-Dist: pytest-cov>=1.8.0; extra == "tests"
Requires-Dist: pytest-xdist>=1.15.0; extra == "tests"
Requires-Dist: requests-mock>=1.5.2; extra == "tests"
Requires-Dist: ruff; extra == "tests"
Requires-Dist: sphinx_rtd_theme>=1.0; extra == "tests"
Requires-Dist: sphinx-argparse>=0.1.15; extra == "tests"
Requires-Dist: Sphinx>=1.4.9; extra == "tests"
Requires-Dist: types-setuptools<75.8.2.20250305; extra == "tests"
Requires-Dist: types-PyYAML; extra == "tests"
Requires-Dist: types-requests; extra == "tests"
Provides-Extra: prospector
Requires-Dist: prospector[with_everything]==1.16.1; extra == "prospector"
Requires-Dist: pytest>=3.10.1; extra == "prospector"
Dynamic: author
Dynamic: author-email
Dynamic: classifier
Dynamic: description
Dynamic: description-content-type
Dynamic: home-page
Dynamic: keywords
Dynamic: license
Dynamic: license-file
Dynamic: platform
Dynamic: provides-extra
Dynamic: requires-dist
Dynamic: requires-python
Dynamic: summary
